gumlet_python_sdk-1.0.0.dist-info/licenses/LICENSE
gumletrestapis/__init__.py
gumletrestapis/api_helper.py
gumletrestapis/configuration.py
gumletrestapis/gumletrestapis_client.py
gumletrestapis/controllers/__init__.py
gumletrestapis/controllers/api_endpoints_controller.py
gumletrestapis/controllers/base_controller.py
gumletrestapis/exceptions/__init__.py
gumletrestapis/exceptions/api_exception.py
gumletrestapis/exceptions/image_analytics_400_error_exception.py
gumletrestapis/exceptions/image_sources_400_error_3_exception.py
gumletrestapis/exceptions/image_sources_400_error_exception.py
gumletrestapis/exceptions/insights_aggregated_data_400_error_exception.py
gumletrestapis/exceptions/insights_aggregated_data_401_error_exception.py
gumletrestapis/exceptions/insights_breakdown_data_400_error_exception.py
gumletrestapis/exceptions/insights_breakdown_data_401_error_exception.py
gumletrestapis/exceptions/insights_chart_data_400_error_exception.py
gumletrestapis/exceptions/insights_chart_data_401_error_exception.py
gumletrestapis/exceptions/video_analytics_400_error_exception.py
gumletrestapis/exceptions/video_assets_400_error_exception.py
gumletrestapis/exceptions/video_assets_401_error_exception.py
gumletrestapis/exceptions/video_assets_list_400_error_exception.py
gumletrestapis/exceptions/video_assets_list_401_error_exception.py
gumletrestapis/exceptions/video_assets_upload_400_error_exception.py
gumletrestapis/exceptions/video_assets_upload_401_error_exception.py
gumletrestapis/exceptions/video_live_assets_400_error_exception.py
gumletrestapis/exceptions/video_live_assets_401_error_exception.py
gumletrestapis/exceptions/video_live_assets_complete_400_error_exception.py
gumletrestapis/exceptions/video_live_assets_copy_400_error_exception.py
gumletrestapis/exceptions/video_live_assets_copy_401_error_exception.py
gumletrestapis/exceptions/video_live_assets_list_400_error_exception.py
gumletrestapis/exceptions/video_live_assets_list_401_error_exception.py
gumlet_python_sdk-1.0.0.dist-info/METADATA
gumlet_python_sdk-1.0.0.dist-info/WHEEL
gumlet_python_sdk-1.0.0.dist-info/top_level.txt
gumlet_python_sdk-1.0.0.dist-info/RECORD
