Metadata-Version: 2.4
Name: gumlet-python-sdk
Version: 1.0.0
Summary: Use Gumlet SDK to upload videos to Gumlet, manage channel & playlist, create image source, and get analytics
Author-email: akbansa <support@gumlet.com>
Project-URL: Documentation, https://docs.gumlet.com/reference/getting-started
Keywords: gumlet,video api,image api,video security,video analytics
Requires-Python: >=3.7
License-File: LICENSE
Requires-Dist: apimatic-core>=0.2.17,~=0.2.0
Requires-Dist: apimatic-core-interfaces>=0.1.5,~=0.1.0
Requires-Dist: apimatic-requests-client-adapter>=0.1.6,~=0.1.0
Provides-Extra: testutils
Requires-Dist: pytest>=7.2.2; extra == "testutils"
Dynamic: license-file
